[
  {
    "expression": "(((((ret_7 / 0.09432615) - 0.04622379) / square(vratio_20)) + (((range_1 + ret_7) + ret_20) / -0.1657566)) * range_1) / ((range_pos_50 / vratio_3) - -0.3074904)",
    "raw_expression": "(((((ret_7 / 0.09432615) - 0.04622379) / square(vratio_20)) + (((range_1 + ret_7) + ret_20) / -0.1657566)) * range_1) / ((range_pos_50 / vratio_3) - -0.3074904)",
    "complexity": 24,
    "loss": 6.79283e-06,
    "score": 0.004149000119673668,
    "regime": "BULL_PULLBACK",
    "horizon": 5
  },
  {
    "expression": "((range_1 / ((range_pos_50 / vratio_3) - -0.26682553)) * ((ret_20 / -0.15224373) + (((ret_7 / 0.11747777) + -0.04644077) / square(vratio_20)))) + square(ret_30)",
    "raw_expression": "((range_1 / ((range_pos_50 / vratio_3) - -0.26682553)) * ((ret_20 / -0.15224373) + (((ret_7 / 0.11747777) + -0.04644077) / square(vratio_20)))) + square(ret_30)",
    "complexity": 23,
    "loss": 6.821072e-06,
    "score": 0.0001804538837846951,
    "regime": "BULL_PULLBACK",
    "horizon": 5
  },
  {
    "expression": "(((((ret_7 / 0.09432615) - 0.04622379) / square(vratio_20)) + ((ret_5 + ret_20) / -0.1657566)) * range_1) / ((range_pos_50 / vratio_3) - -0.3074904)",
    "raw_expression": "(((((ret_7 / 0.09432615) - 0.04622379) / square(vratio_20)) + ((ret_5 + ret_20) / -0.1657566)) * range_1) / ((range_pos_50 / vratio_3) - -0.3074904)",
    "complexity": 22,
    "loss": 6.822303e-06,
    "score": 0.0006925778691858919,
    "regime": "BULL_PULLBACK",
    "horizon": 5
  },
  {
    "expression": "(range_1 * ((((ret_7 / 0.11563999) + -0.04320089) / square(vratio_20)) + (ret_20 / -0.1344065))) / ((range_pos_50 / vratio_3) - -0.25829512)",
    "raw_expression": "range_1*(ret_20/(-0.15224373) + (ret_7/0.11747777 - 0.04644077)/(vratio_20**2))/(range_pos_50/vratio_3 - 1*(-0.26682553)) + ret_30**2",
    "complexity": 20,
    "loss": 6.8317595e-06,
    "score": 0.0030080918390662757,
    "regime": "BULL_PULLBACK",
    "horizon": 5
  },
  {
    "expression": "((range_1 / ((range_pos_50 + 0.25005633) * 0.108901866)) * ((((ret_7 / vratio_20) + -0.011426224) / vratio_20) - ret_20)) - -0.00012772578",
    "raw_expression": "range_1*((ret_20 + ret_5)/(-0.1657566) + (ret_7/0.09432615 - 1*0.04622379)/(vratio_20**2))/(range_pos_50/vratio_3 - 1*(-0.3074904))",
    "complexity": 19,
    "loss": 6.852341e-06,
    "score": 0.0008830307306778856,
    "regime": "BULL_PULLBACK",
    "horizon": 5
  },
  {
    "expression": "(range_1 * ((((ret_7 / 0.14784421) - 0.02840794) / square(vratio_20)) + (ret_20 / -0.1638198))) / (range_pos_50 - -0.20428196)",
    "raw_expression": "range_1*(ret_20/(-0.1344065) + (ret_7/0.11563999 - 0.04320089)/(vratio_20**2))/(range_pos_50/vratio_3 - 1*(-0.25829512))",
    "complexity": 18,
    "loss": 6.8583945e-06,
    "score": 0.00014645212465036242,
    "regime": "BULL_PULLBACK",
    "horizon": 5
  },
  {
    "expression": "range_1 * (((((ret_7 + -0.0048567243) / vratio_20) / vratio_20) - ret_20) / ((0.21084741 + range_pos_50) * 0.15494704))",
    "raw_expression": "range_1*(-ret_20 + (ret_7/vratio_20 - 0.011426224)/vratio_20)/(((range_pos_50 + 0.25005633)*0.108901866)) - 1*(-0.00012772578)",
    "complexity": 17,
    "loss": 6.859399e-06,
    "score": 0.004145113807260756,
    "regime": "BULL_PULLBACK",
    "horizon": 5
  },
  {
    "expression": "(((((ret_7 + -0.00665494) / vratio_20) / vratio_20) - ret_30) * range_1) / (square(range_pos_50) + 0.044920173)",
    "raw_expression": "range_1*(ret_20/(-0.1638198) + (ret_7/0.14784421 - 1*0.02840794)/(vratio_20**2))/(range_pos_50 - 1*(-0.20428196))",
    "complexity": 16,
    "loss": 6.887891e-06,
    "score": 0.001391388098767568,
    "regime": "BULL_PULLBACK",
    "horizon": 5
  },
  {
    "expression": "(range_1 * ((((ret_7 + -0.0037801028) / vratio_20) / vratio_20) - ret_20)) / (ret_7 + 0.064989544)",
    "raw_expression": "range_1*(-ret_20 + (ret_7 - 0.0048567243)/(vratio_20*vratio_20))/(((range_pos_50 + 0.21084741)*0.15494704))",
    "complexity": 15,
    "loss": 6.8974814e-06,
    "score": 0.004317405321063499,
    "regime": "BULL_PULLBACK",
    "horizon": 5
  },
  {
    "expression": "range_1 * (((((ret_7 - ret_2) + -0.0042575835) / square(vratio_20)) - ret_20) / 0.067330875)",
    "raw_expression": "range_1*(-ret_30 + (ret_7 - 0.00665494)/(vratio_20*vratio_20))/(range_pos_50**2 + 0.044920173)",
    "complexity": 14,
    "loss": 6.927325e-06,
    "score": 0.0014918553663051297,
    "regime": "BULL_PULLBACK",
    "horizon": 5
  },
  {
    "expression": "range_1 * ((((ret_7 + -0.003904867) / square(vratio_20)) - ret_20) / 0.06422983)",
    "raw_expression": "range_1*(-ret_20 + (-ret_2 + ret_7 - 0.0042575835)/(vratio_20**2))/0.067330875",
    "complexity": 12,
    "loss": 6.948025e-06,
    "score": 0.015238599327848141,
    "regime": "BULL_PULLBACK",
    "horizon": 5
  },
  {
    "expression": "(((ret_7 + -0.008519256) / vratio_20) - ret_20) * (range_1 / 0.052733522)",
    "raw_expression": "range_1*(-ret_20 + (ret_7 - 0.003904867)/(vratio_20**2))/0.06422983",
    "complexity": 11,
    "loss": 7.054714e-06,
    "score": 0.004149816894243338,
    "regime": "BULL_PULLBACK",
    "horizon": 5
  },
  {
    "expression": "(range_1 * ((ret_7 / square(vratio_20)) - ret_20)) / 0.062169254",
    "raw_expression": "range_1*(-ret_20 + (ret_7 - 0.008519256)/vratio_20)/0.052733522",
    "complexity": 10,
    "loss": 7.0840506e-06,
    "score": 0.0026098420708030603,
    "regime": "BULL_PULLBACK",
    "horizon": 5
  },
  {
    "expression": "(vratio_20 + -0.762859) * (ret_30 * (-0.12853198 / vratio_5))",
    "raw_expression": "range_1*(-ret_20 + ret_7/(vratio_20**2))/0.062169254",
    "complexity": 9,
    "loss": 7.102563e-06,
    "score": 0.00774298468661111,
    "regime": "BULL_PULLBACK",
    "horizon": 5
  },
  {
    "expression": "ret_20 * (square(vratio_20) * (range_1 - range_50))",
    "raw_expression": "(vratio_20 - 0.762859)*ret_30*(-0.12853198)/vratio_5",
    "complexity": 8,
    "loss": 7.1577715e-06,
    "score": 0.0016590281091419467,
    "regime": "BULL_PULLBACK",
    "horizon": 5
  },
  {
    "expression": "(vol_5 * ret_20) / (-0.061364826 / vratio_20)",
    "raw_expression": "ret_20*vratio_20**2*(range_1 - range_50)",
    "complexity": 7,
    "loss": 7.1696563e-06,
    "score": 0.006336352130842588,
    "regime": "BULL_PULLBACK",
    "horizon": 5
  },
  {
    "expression": "(range_1 / square(vratio_20)) * -0.06479482",
    "raw_expression": "ret_20*vol_5/((-0.061364826/vratio_20))",
    "complexity": 6,
    "loss": 7.21523e-06,
    "score": 0.003893740478687844,
    "regime": "BULL_PULLBACK",
    "horizon": 5
  },
  {
    "expression": "(vratio_20 * -0.047836103) * ret_20",
    "raw_expression": "range_1*(-0.06479482)/vratio_20**2",
    "complexity": 5,
    "loss": 7.243379e-06,
    "score": 0.005206431490271916,
    "regime": "BULL_PULLBACK",
    "horizon": 5
  },
  {
    "expression": "square(ret_30) * vratio_20",
    "raw_expression": "vratio_20*(-0.047836103)*ret_20",
    "complexity": 4,
    "loss": 7.2811895e-06,
    "score": 0.003665818207245949,
    "regime": "BULL_PULLBACK",
    "horizon": 5
  },
  {
    "expression": "ret_30 * ret_50",
    "raw_expression": "ret_30**2*vratio_20",
    "complexity": 3,
    "loss": 7.30793e-06,
    "score": 0.0015438962699001713,
    "regime": "BULL_PULLBACK",
    "horizon": 5
  }
]